my_ip/__init__.py
my_ip/console.py
my_ip/core.py
my_ip/data/config.toml
my_ip/settings.py
my_ip-0.2.1.dist-info/entry_points.txt
my_ip-0.2.1.dist-info/LICENSE
my_ip-0.2.1.dist-info/WHEEL
my_ip-0.2.1.dist-info/METADATA
my_ip-0.2.1.dist-info/RECORD
