Metadata-Version: 2.1
Name: my-ip
Version: 0.2.1
Summary: Get your internet IP. Fast.
Home-page: https://github.com/lainiwa/my-ip
License: MIT
Author: lainiwa
Author-email: kirrik96@gmail.com
Requires-Python: >=3.7,<4.0
Classifier: Development Status :: 3 - Alpha
Classifier: Environment :: Console
Classifier: Intended Audience :: End Users/Desktop
Classifier: License :: OSI Approved :: MIT License
Classifier: Natural Language :: English
Classifier: Operating System :: POSIX :: Linux
Classifier: Programming Language :: Python :: 3
Classifier: Programming Language :: Python :: 3.7
Classifier: Topic :: Utilities
Requires-Dist: asks (>=2.3,<3.0)
Requires-Dist: click (>=7.0,<8.0)
Requires-Dist: importlib_metadata (>=0.23.0,<0.24.0)
Requires-Dist: loguru (>=0.3.2,<0.4.0)
Requires-Dist: pydantic (>=1.0,<2.0)
Requires-Dist: pyxdg (>=0.26.0,<0.27.0)
Requires-Dist: toml (>=0.10.0,<0.11.0)
Requires-Dist: trio (>=0.13.0,<0.14.0)
Project-URL: Repository, https://github.com/lainiwa/my-ip
